tclient.py
trans_client-1.0.4.dist-info/LICENSE
trans_client-1.0.4.dist-info/METADATA
trans_client-1.0.4.dist-info/WHEEL
trans_client-1.0.4.dist-info/entry_points.txt
trans_client-1.0.4.dist-info/top_level.txt
trans_client-1.0.4.dist-info/RECORD
