Metadata-Version: 2.1
Name: trans-client
Version: 1.0.4
Summary: A data exchange script based on ssh
Author: fetch150zy
Author-email: zhewei@stu.xidian.edu.cn
License: MIT
Requires-Python: >=3.8
License-File: LICENSE
